mymenu/__init__.py
mymenu/__main__.py
mymenu/menu.py
mymenu-1.2.7.dist-info/METADATA
mymenu-1.2.7.dist-info/WHEEL
mymenu-1.2.7.dist-info/entry_points.txt
mymenu-1.2.7.dist-info/licenses/LICENSE
mymenu-1.2.7.dist-info/RECORD
