Metadata-Version: 2.4
Name: mymenu
Version: 1.2.7
Summary: Menu for your remote console
Project-URL: Homepage, https://codeberg.org/berk76/mymenu
Project-URL: Repository, https://codeberg.org/berk76/mymenu
Project-URL: Issues, https://codeberg.org/berk76/mymenu/issues
Author-email: Jaroslav Beran <jaroslav.beran@gmail.com>
License-Expression: GPL-3.0
License-File: LICENSE
Requires-Python: >=3.10
